fstflow/__init__.py
fstflow-0.1.0.dist-info/WHEEL
fstflow-0.1.0.dist-info/entry_points.txt
fstflow-0.1.0.dist-info/METADATA
fstflow-0.1.0.dist-info/RECORD
