Metadata-Version: 2.3
Name: fstflow
Version: 0.1.0
Summary: A Python library to simplify the creation and manipulation of finite state transducers
Keywords: finite state transducer,fst,nlp,text processing
Author: Pedro José Mora Gallegos
Author-email: Pedro José Mora Gallegos <pedrojosemoragallegos@outlook.de>
Classifier: Development Status :: 3 - Alpha
Classifier: Intended Audience :: Developers
Classifier: Topic :: Software Development :: Libraries
Classifier: Topic :: Text Processing
Classifier: License :: OSI Approved :: MIT License
Classifier: Programming Language :: Python :: 3
Classifier: Programming Language :: Python :: 3.12
Classifier: Programming Language :: Python :: 3.13
Requires-Python: >=3.12
